{
  "background": "The PACFISH/INFISH (PIBO) Effectiveness Monitoring Program for aquatic and riparian resources was developed in 1998 in response to monitoring needs addressed in the Biological Opinions for bull trout (USFWS 1998) and steelhead (NMFS 1995). The primary objective is to determine whether priority biological and physical attributes, processes, and functions of riparian and aquatic systems are being degraded, maintained, or restored in the PIBO area. The program samples within the interior Columbia River basin on lands managed by U.S. Forest Service (FS) Regions 1, 4, and 6 and the Idaho and Oregon/Washington State Offices of the Bureau of Land Management (BLM).This document (hereafter the PIBO Monitoring Protocol) describes the sampling methods used by the PIBO Monitoring Program to quantify stream and riparian attributes. The methods are a result of over two decades of use, evaluation, and peer review. We worked with the Aquatic and Riparian Effectiveness Monitoring Program to standardize methods, which resulted in a document titled Effectiveness Monitoring for Streams and Riparian Areas within the Pacific Northwest: Stream Channel Methods for Core Attributes (USDA 2006).",
  "url": "http://www.monitoringresources.org/api/v1/protocols/3552",
  "title": "PIBO - Sampling Protocol for Stream Channel Attributes",
  "id": 3552,
  "assumptions": "Methods are a result of 11 years of use, evaluation, and peer review. We worked with the Aquatic and Riparian Effectiveness Monitoring Program to standardize methods, which resulted in a document titled &ldquo;Effectiveness Monitoring for Streams and Riparian Areas within the Pacific Northwest: Stream Channel Methods for Core Attributes&rdquo; (USDA 2006).",
  "methods": [
    "http://www.monitoringresources.org/api/v1/methods/55",
    "http://www.monitoringresources.org/api/v1/methods/56",
    "http://www.monitoringresources.org/api/v1/methods/58",
    "http://www.monitoringresources.org/api/v1/methods/59",
    "http://www.monitoringresources.org/api/v1/methods/60",
    "http://www.monitoringresources.org/api/v1/methods/61",
    "http://www.monitoringresources.org/api/v1/methods/62",
    "http://www.monitoringresources.org/api/v1/methods/65",
    "http://www.monitoringresources.org/api/v1/methods/68",
    "http://www.monitoringresources.org/api/v1/methods/69",
    "http://www.monitoringresources.org/api/v1/methods/70",
    "http://www.monitoringresources.org/api/v1/methods/99",
    "http://www.monitoringresources.org/api/v1/methods/101",
    "http://www.monitoringresources.org/api/v1/methods/923",
    "http://www.monitoringresources.org/api/v1/methods/924",
    "http://www.monitoringresources.org/api/v1/methods/4245",
    "http://www.monitoringresources.org/api/v1/methods/6797",
    "http://www.monitoringresources.org/api/v1/methods/6799",
    "http://www.monitoringresources.org/api/v1/methods/6862",
    "http://www.monitoringresources.org/api/v1/methods/6863",
    "http://www.monitoringresources.org/api/v1/methods/6868",
    "http://www.monitoringresources.org/api/v1/methods/6869",
    "http://www.monitoringresources.org/api/v1/methods/6871",
    "http://www.monitoringresources.org/api/v1/methods/6872",
    "http://www.monitoringresources.org/api/v1/methods/6976",
    "http://www.monitoringresources.org/api/v1/methods/7007",
    "http://www.monitoringresources.org/api/v1/methods/7025",
    "http://www.monitoringresources.org/api/v1/methods/7047",
    "http://www.monitoringresources.org/api/v1/methods/7056",
    "http://www.monitoringresources.org/api/v1/methods/7057",
    "http://www.monitoringresources.org/api/v1/methods/7064",
    "http://www.monitoringresources.org/api/v1/methods/7077",
    "http://www.monitoringresources.org/api/v1/methods/7084"
  ],
  "metrics": [
    {
      "id": 15,
      "title": "Pool Frequency",
      "category": "Landscape Form & Geomorphology",
      "subcategory": "Abundance of Habitat Types",
      "isIndicator": false
    },
    {
      "id": 15,
      "title": "Stream flow",
      "category": "Landscape Form & Geomorphology",
      "subcategory": "Abundance of Habitat Types",
      "isIndicator": false
    },
    {
      "id": 19,
      "title": "Bank Type",
      "category": "Landscape Form & Geomorphology",
      "subcategory": "Composition/Structure of Habitat Types",
      "isIndicator": false
    },
    {
      "id": 25,
      "title": "Large wood",
      "category": "Landscape Form & Geomorphology",
      "subcategory": "Distribution of Instream Wood",
      "isIndicator": false
    },
    {
      "id": 28,
      "title": "Disturbances",
      "category": "Disturbance/Restoration",
      "subcategory": "Disturbance Presence",
      "isIndicator": false
    },
    {
      "id": 29,
      "title": "Edge/Density/Sinuosity",
      "category": "Landscape Form & Geomorphology",
      "subcategory": "Edge/Density/Sinuosity",
      "isIndicator": false
    },
    {
      "id": 32,
      "title": "Reach Gradient",
      "category": "Landscape Form & Geomorphology",
      "subcategory": "Gradient",
      "isIndicator": false
    },
    {
      "id": 37,
      "title": "Pool Depth",
      "category": "Landscape Form & Geomorphology",
      "subcategory": "Depth: Pool",
      "isIndicator": false
    },
    {
      "id": 44,
      "title": "Bankfull Width",
      "category": "Landscape Form & Geomorphology",
      "subcategory": "Width: Bankfull ",
      "isIndicator": false
    },
    {
      "id": 112,
      "title": "Macroinvertebrate abundances",
      "category": "Macroinvertebrates",
      "subcategory": "Abundance of Macroinvertebrates",
      "isIndicator": false
    },
    {
      "id": 132,
      "title": "Substrate D50 (Median Particle Size)",
      "category": "Sediment/Substrate/Soils",
      "subcategory": "Composition: Substrate/Soil-Dominant Size",
      "isIndicator": false
    },
    {
      "id": 154,
      "title": "Conductivity",
      "category": "Water Quality",
      "subcategory": "Conductivity",
      "isIndicator": false
    },
    {
      "id": 188,
      "title": "Depth/Height Bankfull",
      "category": "Landscape Form & Geomorphology",
      "subcategory": "Depth/Height: Bankfull ",
      "isIndicator": false
    },
    {
      "id": 197,
      "title": "Bank Angle (Structural Stability)",
      "category": "Landscape Form & Geomorphology",
      "subcategory": "Structural Stability",
      "isIndicator": false
    },
    {
      "id": 208,
      "title": "Side channel",
      "category": "Hydrology/Water Quantity",
      "subcategory": "Presence of Stream Types",
      "isIndicator": false
    },
    {
      "id": 218,
      "title": "Site location",
      "category": "Other",
      "subcategory": "Location",
      "isIndicator": false
    },
    {
      "id": 219,
      "title": "Site photos",
      "category": "Other",
      "subcategory": "Photo Documentation",
      "isIndicator": false
    },
    {
      "id": 225,
      "title": "Pool Tail Fines < 2mm",
      "category": "Sediment/Substrate/Soils",
      "subcategory": "Distribution of Sediment",
      "isIndicator": false
    },
    {
      "id": 225,
      "title": "Pool Tail Fines < 6mm",
      "category": "Sediment/Substrate/Soils",
      "subcategory": "Distribution of Sediment",
      "isIndicator": false
    },
    {
      "id": 228,
      "title": "Bank material",
      "category": "Sediment/Substrate/Soils",
      "subcategory": "Type of Substrate",
      "isIndicator": false
    },
    {
      "id": 242,
      "title": "Alkalinity",
      "category": "Water Quality",
      "subcategory": "Alkalinity",
      "isIndicator": false
    },
    {
      "id": 369,
      "title": "Pool Characteristics and Qualifications",
      "category": "Landscape Form & Geomorphology",
      "subcategory": "Aquatic or Floodplain Geomorphology:  Area",
      "isIndicator": false
    },
    {
      "id": 394,
      "title": "Beaver Presence",
      "category": "Mammals",
      "subcategory": "Presence/Absence: Mammals",
      "isIndicator": false
    }
  ],
  "objectives": [
    "Determine if specific Designated Management Area practices related to livestock grazing are maintaining or restoring riparian vegetation structure and function.",
    "Determine the direction and rate of change in riparian and aquatic habitats over time as a function of management practices.",
    "Determine whether a suite of biological and physical attributes, processes, and functions of upland, riparian, and aquatic systems are being degraded, maintained, or restored across the PIBO landscape"
  ],
  "ownerName": "PNAMP Support",
  "ownerEmail": "pnamp.mm@gmail.com",
  "programUrl": "http://www.monitoringresources.org/api/v1/programs/5",
  "vector": [
    -0.0018222435610368848,
    -0.024671288207173347,
    0.012172160670161247,
    -0.026574276387691498,
    0.04212565720081329,
    -0.020632954314351082,
    -0.018799416720867157,
    0.02069767564535141,
    -0.030647993087768555,
    0.03316232189536095,
    -0.08409606665372849,
    -0.0934705138206482,
    -0.04267774149775505,
    0.03809573873877525,
    -0.06794026494026184,
    0.06180291250348091,
    0.06071384996175766,
    -0.020994843915104866,
    -0.05052267014980316,
    0.014932394959032536,
    0.03365800529718399,
    0.02676037698984146,
    -0.0688805878162384,
    -0.05386371165513992,
    -0.06332055479288101,
    -0.020886661484837532,
    -0.14169761538505554,
    -0.004428633488714695,
    -0.019263621419668198,
    -0.005785997025668621,
    -0.0017044930718839169,
    0.030757566913962364,
    0.07201410084962845,
    -0.029207417741417885,
    -0.0015594505239278078,
    0.02799738384783268,
    0.03406262770295143,
    -0.05921071022748947,
    -0.05099191889166832,
    0.09627605974674225,
    -0.012586855329573154,
    0.017489343881607056,
    0.0026389118283987045,
    0.045939937233924866,
    -0.055195871740579605,
    0.025809749960899353,
    -0.03056875616312027,
    -0.042761191725730896,
    -0.04793107882142067,
    0.01781523786485195,
    -0.002659064717590809,
    -0.04420587047934532,
    -0.016511518508195877,
    0.09971980005502701,
    -0.004113039001822472,
    -0.0363471694290638,
    -0.07989770919084549,
    -0.05648697167634964,
    -0.0254519023001194,
    -0.037078872323036194,
    -0.01395209040492773,
    0.01855192892253399,
    -0.05330957472324371,
    0.019712315872311592,
    0.012350499629974365,
    0.030375581234693527,
    -0.06988345831632614,
    0.03238971158862114,
    0.04326236620545387,
    -0.10773377865552902,
    -0.005623014643788338,
    -0.00012168114335509017,
    -0.08338718116283417,
    0.0014186437474563718,
    -0.05582842230796814,
    0.03390912711620331,
    0.022985411807894707,
    0.08704748749732971,
    0.046960677951574326,
    -0.11537900567054749,
    -0.034242186695337296,
    -0.038811203092336655,
    0.013924136757850647,
    -0.02629409171640873,
    0.07229811698198318,
    0.08865635842084885,
    -0.02556743286550045,
    0.059436798095703125,
    -0.0359603576362133,
    0.01678300090134144,
    0.051675669848918915,
    0.02981792390346527,
    0.054523203521966934,
    -0.05018770694732666,
    -0.025428546592593193,
    0.03029509074985981,
    -0.0026551091577857733,
    -0.06506840884685516,
    -0.040494807064533234,
    0.030510591343045235,
    0.013831004500389099,
    -0.04555552452802658,
    -0.012972895056009293,
    -0.13870494067668915,
    0.03438965231180191,
    -0.07347553968429565,
    -0.058836933225393295,
    0.1263340711593628,
    0.05589153617620468,
    0.0700930505990982,
    -0.05936167389154434,
    0.02325768768787384,
    0.045752692967653275,
    0.10179257392883301,
    0.11474857479333878,
    0.04144938662648201,
    0.021317286416888237,
    -0.03383928909897804,
    0.030768202617764473,
    -0.06482335180044174,
    -0.005816382821649313,
    -0.052790578454732895,
    0.030412787571549416,
    -0.024095997214317322,
    0.06530450284481049,
    0.07367226481437683,
    0.006617915350943804,
    1.4350457993712525e-33,
    0.050457168370485306,
    -0.02894352562725544,
    -0.023588664829730988,
    -0.06543821096420288,
    -0.07249502092599869,
    -0.051336660981178284,
    -0.008394895121455193,
    -0.052512429654598236,
    0.033312585204839706,
    0.007973908446729183,
    0.010114616714417934,
    0.11471730470657349,
    -0.008519969880580902,
    0.06558392941951752,
    0.045007430016994476,
    0.006679033860564232,
    -0.026705298572778702,
    0.022489802911877632,
    0.0037425761111080647,
    -0.02843228541314602,
    -0.02432567998766899,
    -0.03587138280272484,
    0.007256227545440197,
    -0.020505476742982864,
    0.04170461744070053,
    -0.022064074873924255,
    -0.002978564938530326,
    -0.004774600267410278,
    -0.0942642092704773,
    0.025844058021903038,
    0.05828684940934181,
    -0.08895792812108994,
    -0.03806743398308754,
    -0.025713888928294182,
    0.014993677847087383,
    -0.05777072161436081,
    0.06102635711431503,
    0.040789976716041565,
    -0.04747946560382843,
    0.03309496492147446,
    0.011399736627936363,
    -0.031014537438750267,
    0.028245413675904274,
    0.01011650636792183,
    0.060553472489118576,
    -0.06349223107099533,
    0.07026086002588272,
    0.0734795331954956,
    -0.00551017839461565,
    0.01063207071274519,
    0.043452683836221695,
    0.02004845254123211,
    0.09455366432666779,
    0.0005143459420651197,
    -0.047117896378040314,
    0.11600126326084137,
    0.029827527701854706,
    -0.010145933367311954,
    -0.03623952344059944,
    0.003635407891124487,
    0.007626810576766729,
    0.07872141152620316,
    0.007404899690300226,
    -0.06358706951141357,
    0.025819217786192894,
    -0.012977128848433495,
    0.03517404943704605,
    0.09201452136039734,
    0.017069710418581963,
    -0.027395565062761307,
    -0.022738568484783173,
    -0.06462817639112473,
    -0.05964161083102226,
    0.016035187989473343,
    0.0013191994512453675,
    -0.05164285749197006,
    0.04955329746007919,
    0.023912066593766212,
    -0.00493948720395565,
    0.02025717869400978,
    -0.025402259081602097,
    0.01616041176021099,
    0.02310962788760662,
    0.06953849643468857,
    -0.058075692504644394,
    0.05237537622451782,
    0.09733999520540237,
    -0.042765889316797256,
    -0.04618128016591072,
    -0.016437474638223648,
    0.043553490191698074,
    0.042179007083177567,
    -0.03355574607849121,
    -0.011042867787182331,
    0.06899985671043396,
    -1.4676552065245128e-33,
    0.00657258927822113,
    -0.011386682279407978,
    -0.018427902832627296,
    0.05187828838825226,
    0.0209767185151577,
    -0.1253567337989807,
    0.013554273173213005,
    -0.016699843108654022,
    0.122198186814785,
    -0.11338598281145096,
    -0.06596808135509491,
    0.027670659124851227,
    -0.0391022190451622,
    0.05613420903682709,
    0.05565454065799713,
    -0.022559087723493576,
    -0.07173189520835876,
    -0.052497498691082,
    -0.03925424441695213,
    -0.06348731368780136,
    -0.07238924503326416,
    -0.03740878403186798,
    -0.011483405716717243,
    0.07415167987346649,
    -0.04709096997976303,
    0.06194709986448288,
    -0.019964339211583138,
    -0.05080880597233772,
    0.07181455940008163,
    -0.11257460713386536,
    0.03676251322031021,
    0.010865367017686367,
    0.02622336708009243,
    -0.006555995438247919,
    -0.06469566375017166,
    -0.025389844551682472,
    0.09529279917478561,
    -0.04447846859693527,
    -0.0019027830567210913,
    0.026846732944250107,
    0.0808415561914444,
    0.03487081453204155,
    -0.03285260871052742,
    -0.03802158311009407,
    -0.04320831224322319,
    0.0999111458659172,
    0.003919012378901243,
    0.009054257534444332,
    -0.09974376857280731,
    0.04351917654275894,
    0.038701727986335754,
    0.030154798179864883,
    -0.02552133984863758,
    0.06288941204547882,
    0.06565883755683899,
    -0.00616409769281745,
    0.07104013860225677,
    0.04605075344443321,
    -0.07992051541805267,
    -0.024103354662656784,
    -0.043222300708293915,
    0.0720347911119461,
    -0.04909032583236694,
    0.027284016832709312,
    0.04205434024333954,
    0.05373038724064827,
    0.08125460892915726,
    -0.06040452420711517,
    -0.046806029975414276,
    -0.004223817493766546,
    0.0082636009901762,
    -0.01067021582275629,
    -0.040582798421382904,
    -0.05478817597031593,
    -0.0036215572617948055,
    -0.021233337000012398,
    -0.04514918848872185,
    -0.005705177318304777,
    -0.023243920877575874,
    0.02945828065276146,
    0.002473935717716813,
    -0.02633812464773655,
    -0.004496442154049873,
    0.0005900025716982782,
    0.03121114708483219,
    0.015033825300633907,
    -0.027055086567997932,
    -0.11123053729534149,
    0.028294946998357773,
    -0.006991465575993061,
    -0.04736095294356346,
    -0.024541182443499565,
    -0.14625464379787445,
    0.05511576682329178,
    -0.0200042687356472,
    -4.027489453051203e-08,
    0.06791134923696518,
    0.04075895622372627,
    -0.07423728704452515,
    0.05294790863990784,
    -0.026141051203012466,
    -0.026789244264364243,
    0.01296473853290081,
    0.006842148490250111,
    -0.029257159680128098,
    -0.0009160111076198518,
    0.019326047971844673,
    -0.0013539110077545047,
    -0.004458272363990545,
    0.020087921991944313,
    0.078252412378788,
    -0.07111260294914246,
    0.11622445285320282,
    -0.042691897600889206,
    -0.05849926546216011,
    -0.001578034250997007,
    -0.06296917796134949,
    0.0009683755342848599,
    0.014593991450965405,
    -0.02076358161866665,
    0.014500943943858147,
    -0.048866063356399536,
    0.021758830174803734,
    0.018304353579878807,
    0.11743824928998947,
    0.054758213460445404,
    0.03236529603600502,
    0.08131281286478043,
    0.013429968617856503,
    0.0177907794713974,
    0.09499426186084747,
    0.0418732725083828,
    -0.04973875358700752,
    0.0018486492335796356,
    0.03361460939049721,
    0.09728530794382095,
    -0.03415955603122711,
    0.09414580464363098,
    -0.08795822411775589,
    0.02311752364039421,
    0.0810302346944809,
    0.021821264177560806,
    0.013868242502212524,
    0.025951175019145012,
    0.07997650653123856,
    -0.11023786664009094,
    0.013726558536291122,
    -0.05417272448539734,
    0.007685639429837465,
    0.05254035443067551,
    -0.01521313190460205,
    0.10300587862730026,
    -0.011826538480818272,
    -0.11184602230787277,
    -0.0018195967422798276,
    0.01779591664671898,
    0.016463138163089752,
    -0.024164827540516853,
    -0.038136839866638184,
    -0.008843527175486088
  ]
}